talentro/__init__.py
talentro/acquisition/__init__.py
talentro/acquisition/dataclasses.py
talentro/acquisition/models.py
talentro/billing/__init__.py
talentro/billing/dataclasses.py
talentro/billing/models.py
talentro/candidates/__init__.py
talentro/candidates/dataclasses.py
talentro/candidates/models.py
talentro/constants.py
talentro/event.py
talentro/exceptions.py
talentro/general/__init__.py
talentro/general/dataclasses.py
talentro/general/models.py
talentro/iam/__init__.py
talentro/iam/dataclasses.py
talentro/iam/models.py
talentro/iam/types.py
talentro/integrations/__init__.py
talentro/integrations/dataclasses.py
talentro/integrations/models.py
talentro/messaging/__init__.py
talentro/messaging/topology.py
talentro/services/__init__.py
talentro/services/billing.py
talentro/services/caching.py
talentro/services/clients.py
talentro/services/db.py
talentro/services/google_storage.py
talentro/services/rabbitmq.py
talentro/util/__init__.py
talentro/util/attributes.py
talentro/util/enum.py
talentro/util/files.py
talentro/util/singleton.py
talentro/util/string.py
talentro/util/vacancy.py
talentro/vacancies/__init__.py
talentro/vacancies/dataclasses.py
talentro/vacancies/models.py
talentro/vacancies/taxanomy.py
talentro_commons-0.21.1.dist-info/METADATA
talentro_commons-0.21.1.dist-info/WHEEL
talentro_commons-0.21.1.dist-info/RECORD
