Metadata-Version: 2.4
Name: talentro-commons
Version: 0.21.1
Summary: This package contains all globally used code, services, models and data structures for Talentro
License: Proprietary
Author: Emiel van Essen
Author-email: emiel@marksmen.nl
Requires-Python: >=3.13,<4.0
Classifier: License :: Other/Proprietary License
Classifier: Programming Language :: Python :: 3
Classifier: Programming Language :: Python :: 3.13
Classifier: Programming Language :: Python :: 3.14
Requires-Dist: aio-pika (>=9.5.7,<10.0.0)
Requires-Dist: aiocache[redis] (>=0.12.3,<0.13.0)
Requires-Dist: fastapi (>=0.128.0,<0.129.0)
Requires-Dist: google-cloud-storage (>=3.6.0,<4.0.0)
Requires-Dist: httpx (>=0.28.1,<0.29.0)
Requires-Dist: sqlalchemy (>=2.0.38,<3.0.0)
Requires-Dist: sqlmodel (>=0.0.31,<0.0.32)
